odoo/addons/l10n_br_nfse_focus/README.rst
odoo/addons/l10n_br_nfse_focus/__init__.py
odoo/addons/l10n_br_nfse_focus/__manifest__.py
odoo/addons/l10n_br_nfse_focus/data/l10n_br_nfse_focus_cron.xml
odoo/addons/l10n_br_nfse_focus/i18n/l10n_br_nfse_focus.pot
odoo/addons/l10n_br_nfse_focus/i18n/pt_BR.po
odoo/addons/l10n_br_nfse_focus/models/__init__.py
odoo/addons/l10n_br_nfse_focus/models/document.py
odoo/addons/l10n_br_nfse_focus/models/res_company.py
odoo/addons/l10n_br_nfse_focus/readme/CONFIGURE.md
odoo/addons/l10n_br_nfse_focus/readme/CONTRIBUTORS.md
odoo/addons/l10n_br_nfse_focus/readme/DESCRIPTION.md
odoo/addons/l10n_br_nfse_focus/readme/INSTALL.md
odoo/addons/l10n_br_nfse_focus/readme/USAGE.md
odoo/addons/l10n_br_nfse_focus/static/description/icon.png
odoo/addons/l10n_br_nfse_focus/static/description/index.html
odoo/addons/l10n_br_nfse_focus/tests/__init__.py
odoo/addons/l10n_br_nfse_focus/tests/test_l10n_br_nfse_focus.py
odoo/addons/l10n_br_nfse_focus/tests/nfse/pdf_example.pdf
odoo/addons/l10n_br_nfse_focus/views/res_company.xml
odoo_addon_l10n_br_nfse_focus-18.0.2.0.0.dist-info/METADATA
odoo_addon_l10n_br_nfse_focus-18.0.2.0.0.dist-info/WHEEL
odoo_addon_l10n_br_nfse_focus-18.0.2.0.0.dist-info/top_level.txt
odoo_addon_l10n_br_nfse_focus-18.0.2.0.0.dist-info/RECORD
