Metadata-Version: 2.1
Name: odoo-addon-l10n_br_nfse_focus
Version: 18.0.2.0.0
Requires-Python: >=3.10
Requires-Dist: odoo-addon-l10n_br_nfse==18.0.*
Requires-Dist: odoo==18.0.*
Summary: NFS-e (FocusNFE)
Home-page: https://github.com/OCA/l10n-brazil
License: AGPL-3
Author: KMEE, Escodoo, Odoo Community Association (OCA)
Author-email: support@odoo-community.org
Classifier: Programming Language :: Python
Classifier: Framework :: Odoo
Classifier: Framework :: Odoo :: 18.0
Classifier: License :: OSI Approved :: GNU Affero General Public License v3
Classifier: Development Status :: 4 - Beta
